{
  "hash": "2e26ef5b",
  "browserHash": "d4991824",
  "optimized": {
    "vue": {
      "src": "../../../../node_modules/.pnpm/vue@3.3.8_typescript@5.2.2/node_modules/vue/dist/vue.runtime.esm-bundler.js",
      "file": "vue.js",
      "fileHash": "54869272",
      "needsInterop": false
    },
    "vitepress > @vue/devtools-api": {
      "src": "../../../../node_modules/.pnpm/@vue+devtools-api@6.5.1/node_modules/@vue/devtools-api/lib/esm/index.js",
      "file": "vitepress___@vue_devtools-api.js",
      "fileHash": "25b9527a",
      "needsInterop": false
    }
  },
  "chunks": {}
}